setup.py
agnostic_loader/__init__.py
agnostic_loader/data_loader.py
agnostic_loader.egg-info/PKG-INFO
agnostic_loader.egg-info/SOURCES.txt
agnostic_loader.egg-info/dependency_links.txt
agnostic_loader.egg-info/not-zip-safe
agnostic_loader.egg-info/top_level.txt