Metadata-Version: 1.0
Name: agnostic-loader
Version: 0.3.1
Summary: Load data from different input sources
Home-page: https://github.com/JulieRossi/agnostic_loader.git
Author: Julie Rossi
Author-email: julierossi06@gmail.com
License: MIT
Platform: UNKNOWN
